onaplogging/__init__.py
onaplogging/colorFormatter.py
onaplogging/logWatchDog.py
onaplogging/markerFormatter.py
onaplogging/markerLogAdaptor.py
onaplogging/mdcContext.py
onaplogging/mdcformatter.py
onaplogging/monkey.py
onaplogging/marker/__init__.py
onaplogging/marker/marker.py
onaplogging/marker/markerFactory.py
onaplogging/marker/markerFilter.py
onaplogging/marker/markerHandler.py
onappylog-1.0.9.dist-info/DESCRIPTION.rst
onappylog-1.0.9.dist-info/METADATA
onappylog-1.0.9.dist-info/RECORD
onappylog-1.0.9.dist-info/WHEEL
onappylog-1.0.9.dist-info/metadata.json
onappylog-1.0.9.dist-info/top_level.txt
tests/__init__.py
tests/test_example.py
